webdriver_manager/__init__.py
webdriver_manager/arg_parser.py
webdriver_manager/commands.py
webdriver_manager/config.py
webdriver_manager/helpers.py
webdriver_manager/logger.py
webdriver_manager/main.py
webdriver_manager/webdriver/__init__.py
webdriver_manager/webdriver/basedriver.py
webdriver_manager/webdriver/chromedriver.py
webdriver_manager/webdriver/geckodriver.py
py_webdriver_manager-0.0.3.dist-info/LICENSE
py_webdriver_manager-0.0.3.dist-info/METADATA
py_webdriver_manager-0.0.3.dist-info/WHEEL
py_webdriver_manager-0.0.3.dist-info/entry_points.txt
py_webdriver_manager-0.0.3.dist-info/top_level.txt
py_webdriver_manager-0.0.3.dist-info/RECORD
