Metadata-Version: 2.1
Name: py-webdriver-manager
Version: 0.0.3
Summary: Webdriver executable manager utility
Home-page: https://github.com/lucianopuccio/webdriver-manager
Author: UNKNOWN
Author-email: UNKNOWN
License: MIT
Keywords: test selenium webdriver webdriver-manager
Platform: UNKNOWN
Classifier: Development Status :: 4 - Beta
Classifier: Programming Language :: Python :: 3.4
Classifier: Programming Language :: Python :: 3.5
Classifier: Programming Language :: Python :: 3.6
Classifier: Natural Language :: English
Classifier: Intended Audience :: Developers
Classifier: License :: OSI Approved :: MIT License
Classifier: Operating System :: OS Independent
Classifier: Topic :: Software Development :: Quality Assurance
Classifier: Topic :: Software Development :: Testing
Requires-Dist: requests
Requires-Dist: tqdm (==4.23.1)
